yapas/__init__.py
yapas/__main__.py
yapas/conf/__init__.py
yapas/conf/dispatcher.py
yapas/conf/loggers.py
yapas/conf/parser.py
yapas/core/__init__.py
yapas/core/abs/__init__.py
yapas/core/abs/cache.py
yapas/core/abs/client.py
yapas/core/abs/dispatcher.py
yapas/core/abs/enums.py
yapas/core/abs/handlers.py
yapas/core/abs/messages.py
yapas/core/abs/server.py
yapas/core/abs/static.py
yapas/core/cache/__init__.py
yapas/core/cache/memory.py
yapas/core/client/__init__.py
yapas/core/client/aiohttp.py
yapas/core/client/socket.py
yapas/core/constants.py
yapas/core/dispatcher.py
yapas/core/exceptions.py
yapas/core/middlewares/__init__.py
yapas/core/middlewares/metrics.py
yapas/core/server/__init__.py
yapas/core/server/django_messages.py
yapas/core/server/handlers.py
yapas/core/server/proxy.py
yapas/core/signals.py
yapas/core/statics.py
yapas/locations.ini
yapas/static/css/min.css
yapas/static/scripts/main.js
yapas/static/templates/base.html
yapas/static/templates/index.html
yapas-0.1.0.dist-info/METADATA
yapas-0.1.0.dist-info/WHEEL
yapas-0.1.0.dist-info/RECORD
