Metadata-Version: 2.1
Name: yapas
Version: 0.1.0
Summary: Yet another Python async server
License: MIT
Author: andrei-samofalov
Author-email: andrei.e.samofalov@gmail.com
Requires-Python: >=3.12,<4.0
Classifier: License :: OSI Approved :: MIT License
Classifier: Programming Language :: Python :: 3
